cleanunet/__init__.py
cleanunet/dataset.py
cleanunet/denoise.py
cleanunet/distributed.py
cleanunet/network.py
cleanunet/python_eval.py
cleanunet/stft_loss.py
cleanunet/train.py
cleanunet/util.py
cleanunet-0.0.3.dist-info/LICENSE
cleanunet-0.0.3.dist-info/METADATA
cleanunet-0.0.3.dist-info/WHEEL
cleanunet-0.0.3.dist-info/top_level.txt
cleanunet-0.0.3.dist-info/RECORD
