Metadata-Version: 2.1
Name: cleanunet
Version: 0.0.3
Summary: CleanUNet - speech Denoiser
Author: Sawradip Saha
Author-email: <sawradip0@gmail.com>
Keywords: python,speech-denoiser
Classifier: Development Status :: 3 - Alpha
Classifier: Intended Audience :: Education
Classifier: Programming Language :: Python :: 2
Classifier: Programming Language :: Python :: 3
Classifier: Operating System :: MacOS :: MacOS X
Classifier: Operating System :: Microsoft :: Windows
License-File: LICENSE
Requires-Dist: pillow
Requires-Dist: torchaudio
Requires-Dist: inflect
Requires-Dist: scipy
Requires-Dist: tqdm
Requires-Dist: pesq
Requires-Dist: pystoi
